myapp/__init__.py
myapp/base.py
myapp/cli.py
mockdatagen-1.1.0.dist-info/LICENSE
mockdatagen-1.1.0.dist-info/METADATA
mockdatagen-1.1.0.dist-info/WHEEL
mockdatagen-1.1.0.dist-info/entry_points.txt
mockdatagen-1.1.0.dist-info/RECORD
