Metadata-Version: 2.3
Name: mockdatagen
Version: 1.1.0
Summary: Generate Synthetic Data for MDM use case
License: MIT
Author: ankit
Author-email: ankit48365@gmail.com
Requires-Python: >=3.9
Classifier: License :: OSI Approved :: MIT License
Classifier: Programming Language :: Python :: 3
Classifier: Programming Language :: Python :: 3.9
Classifier: Programming Language :: Python :: 3.10
Classifier: Programming Language :: Python :: 3.11
Classifier: Programming Language :: Python :: 3.12
Classifier: Programming Language :: Python :: 3.13
Requires-Dist: coverage-badge (>=1.1.2)
Requires-Dist: faker (>=37.4.0)
Requires-Dist: pandas (>=2.3.0)
Requires-Dist: poetry (>=2.1.3)
Requires-Dist: pylint (>=3.3.7)
Requires-Dist: pytest (>=8.4.0)
Requires-Dist: pytest-cov (>=6.2.1)
Requires-Dist: tabulate (>=0.9.0)
